apipy_logs/__init__.py
apipy_logs/log_manager.py
apipy_logs-0.1.2.dist-info/LICENSE
apipy_logs-0.1.2.dist-info/METADATA
apipy_logs-0.1.2.dist-info/WHEEL
apipy_logs-0.1.2.dist-info/top_level.txt
apipy_logs-0.1.2.dist-info/RECORD
