Metadata-Version: 2.2
Name: apipy_logs
Version: 0.1.2
Summary: A package to create, read and delete your logs
Author-email: SebastienCozeDev <contact@cozedev.com>
Project-URL: Homepage, https://github.com/SebastienCozeDev/apipy_logs
Project-URL: Issues, https://github.com/SebastienCozeDev/apipy_logs/issues
Classifier: Programming Language :: Python :: 3.10
Classifier: Operating System :: OS Independent
Classifier: License :: OSI Approved :: Mozilla Public License 2.0 (MPL 2.0)
Requires-Python: >=3.10
License-File: LICENSE
